holoforgecli/__init__.py
holoforgecli/ascii.py
holoforgecli/holo.py
HoloforgeAI_CLI-0.1.0.dist-info/METADATA
HoloforgeAI_CLI-0.1.0.dist-info/WHEEL
HoloforgeAI_CLI-0.1.0.dist-info/entry_points.txt
HoloforgeAI_CLI-0.1.0.dist-info/top_level.txt
HoloforgeAI_CLI-0.1.0.dist-info/RECORD
