Metadata-Version: 2.1
Name: HoloforgeAI-CLI
Version: 0.1.0
Summary: A CLI companion tool for managing Holoforge applications
Home-page: https://gitlab.com/holoforgeai/holoforge-cli
Author: Erik Rowan <erik@holoforge.ai, Gerardo I. Ornelas <gerardo@holoforge.ai>
Author-email: erik@holoforge.ai
Classifier: Programming Language :: Python :: 3
Classifier: License :: OSI Approved :: MIT License
Classifier: Operating System :: OS Independent
Requires-Python: >=3.6
Requires-Dist: boto3
Requires-Dist: requests
Requires-Dist: configparser
